mkdocs_frontmatter_plugin/__init__.py
mkdocs_frontmatter_plugin/config.py
mkdocs_frontmatter_plugin/plugin.py
mkdocs_frontmatter_plugin-0.1.5.dist-info/METADATA
mkdocs_frontmatter_plugin-0.1.5.dist-info/WHEEL
mkdocs_frontmatter_plugin-0.1.5.dist-info/entry_points.txt
mkdocs_frontmatter_plugin-0.1.5.dist-info/RECORD
