Metadata-Version: 2.1
Name: mkdocs-frontmatter-plugin
Version: 0.1.5
Summary: 
Author: Diego Canez
Author-email: canezdiego@gmail.com
Requires-Python: >=3.9,<4.0
Classifier: Programming Language :: Python :: 3
Classifier: Programming Language :: Python :: 3.9
Classifier: Programming Language :: Python :: 3.10
Classifier: Programming Language :: Python :: 3.11
Classifier: Programming Language :: Python :: 3.12
Requires-Dist: mkdocs (>=1.5.3,<2.0.0)
Requires-Dist: mkdocs-roamlinks-plugin (>=0.3.2,<0.4.0)
